cb_logging/__init__.py
cb_logging/cb_logging.py
cb_pingy/__init__.py
cb_pingy/cb_pingy.py
cb_test_rig/__init__.py
cb_test_rig/test_rig_config.py
cb_test_rig/test_rig_status.py
cb_test_rig/test_rig_status_client.py
cb_test_rig_tools/lighthouse.py
examples/cb_logging/example.py
examples/cb_test_rig/example.py
cb_pyutils-0.3.1.dist-info/METADATA
cb_pyutils-0.3.1.dist-info/WHEEL
cb_pyutils-0.3.1.dist-info/entry_points.txt
cb_pyutils-0.3.1.dist-info/licenses/LICENSE
cb_pyutils-0.3.1.dist-info/RECORD
