Metadata-Version: 2.4
Name: cb_pyutils
Version: 0.3.1
Project-URL: Homepage, https://github.com/chriesibaum/cb-pyutils
License-File: LICENSE
Requires-Python: >=3.12
Requires-Dist: busylight-core
Requires-Dist: key-stroke>=1.3.0
Requires-Dist: paho-mqtt
Requires-Dist: ping3
